LICENSE.md
MANIFEST.in
README.md
cl2nc.1
cl2nc.py
pyproject.toml
setup.cfg
setup.py
cl2nc.egg-info/PKG-INFO
cl2nc.egg-info/SOURCES.txt
cl2nc.egg-info/dependency_links.txt
cl2nc.egg-info/entry_points.txt
cl2nc.egg-info/requires.txt
cl2nc.egg-info/top_level.txt